zhixinpy/chart_dialogs.cp311-win_amd64.pyd
zhixinpy/cli.cp311-win_amd64.pyd
zhixinpy/dialog_framework.cp311-win_amd64.pyd
zhixinpy/dialogs_tools.cp311-win_amd64.pyd
zhixinpy/func_calendar.cp311-win_amd64.pyd
zhixinpy/func_chart.cp311-win_amd64.pyd
zhixinpy/func_converter.cp311-win_amd64.pyd
zhixinpy/func_filter.cp311-win_amd64.pyd
zhixinpy/func_kchart.cp311-win_amd64.pyd
zhixinpy/func_lookup.cp311-win_amd64.pyd
zhixinpy/func_rtd.cp311-win_amd64.pyd
zhixinpy/func_series.cp311-win_amd64.pyd
zhixinpy/func_stat.cp311-win_amd64.pyd
zhixinpy/func_text.cp311-win_amd64.pyd
zhixinpy/func_tools.cp311-win_amd64.pyd
zhixinpy/func_upgrade.cp311-win_amd64.pyd
zhixinpy/licclient.cp311-win_amd64.pyd
zhixinpy/ribbon.cp311-win_amd64.pyd
zhixinpy/ribbon_chart_unified.cp311-win_amd64.pyd
zhixinpy/tool_dialogs.cp311-win_amd64.pyd
zhixinpy/utils.cp311-win_amd64.pyd
zhixinpy/zhixinpy.cp311-win_amd64.pyd
zhixinpy-0.2.22.data/data/share/zhixinpy/ExcelDna.IntelliSense64.xll
zhixinpy-0.2.22.data/data/share/zhixinpy/chart-area.png
zhixinpy-0.2.22.data/data/share/zhixinpy/chart-bar-3d.png
zhixinpy-0.2.22.data/data/share/zhixinpy/chart-bar.png
zhixinpy-0.2.22.data/data/share/zhixinpy/chart-funnel.png
zhixinpy-0.2.22.data/data/share/zhixinpy/chart-geo-line.png
zhixinpy-0.2.22.data/data/share/zhixinpy/chart-geo.png
zhixinpy-0.2.22.data/data/share/zhixinpy/chart-heatmap.png
zhixinpy-0.2.22.data/data/share/zhixinpy/chart-kchart.png
zhixinpy-0.2.22.data/data/share/zhixinpy/chart-line.png
zhixinpy-0.2.22.data/data/share/zhixinpy/chart-line3d.png
zhixinpy-0.2.22.data/data/share/zhixinpy/chart-map-bar.png
zhixinpy-0.2.22.data/data/share/zhixinpy/chart-map.png
zhixinpy-0.2.22.data/data/share/zhixinpy/chart-network.png
zhixinpy-0.2.22.data/data/share/zhixinpy/chart-pie-bar.png
zhixinpy-0.2.22.data/data/share/zhixinpy/chart-pie.png
zhixinpy-0.2.22.data/data/share/zhixinpy/chart-rank-wind.png
zhixinpy-0.2.22.data/data/share/zhixinpy/chart-rank.png
zhixinpy-0.2.22.dist-info/LICENSE
zhixinpy-0.2.22.dist-info/METADATA
zhixinpy-0.2.22.dist-info/WHEEL
zhixinpy-0.2.22.dist-info/entry_points.txt
zhixinpy-0.2.22.dist-info/top_level.txt
zhixinpy-0.2.22.dist-info/RECORD
