Metadata-Version: 2.1
Name: zhixinpy
Version: 0.2.22
Summary: Excel Ribbon via Python
Home-page: https://zhixin.readthedocs.io
Author: Morgan Yuan
Author-email: gnyuan@gmail.com
Classifier: Programming Language :: Python :: 3.11
Classifier: Programming Language :: Python :: 3.12
Classifier: Programming Language :: Python :: 3.13
Classifier: License :: OSI Approved :: MIT License
Classifier: Topic :: Office/Business :: Financial :: Spreadsheet
Classifier: Operating System :: Microsoft :: Windows
Requires-Python: >=3.11,<3.14
License-File: LICENSE
Requires-Dist: setuptools ==70.1.0
Requires-Dist: wheel ==0.43.0
Requires-Dist: cython ==3.0.10
Requires-Dist: twine ==6.0.1
Requires-Dist: argparse ==1.4.0
Requires-Dist: numpy
Requires-Dist: scipy
Requires-Dist: pandas
Requires-Dist: scikit-learn
Requires-Dist: statsmodels
Requires-Dist: prophet
Requires-Dist: matplotlib
Requires-Dist: seaborn
Requires-Dist: plotly
Requires-Dist: pyecharts ==2.0.8
Requires-Dist: requests ==2.32.3
Requires-Dist: aiohttp ==3.11.18
Requires-Dist: websockets ==12.0
Requires-Dist: lxml
Requires-Dist: tomlkit ==0.13.2
Requires-Dist: packaging ==24.1
Requires-Dist: pychrome ==0.2.4
Requires-Dist: pywin32
Requires-Dist: keyboard ==0.13.5
Requires-Dist: xloil ==0.21.0
Requires-Dist: cryptography ==42.0.8
Requires-Dist: pycryptodome ==3.20.0
Requires-Dist: openai ==1.97.0
Requires-Dist: jieba ==0.42.1
Requires-Dist: amzqr ==0.0.1
Requires-Dist: pillow
Requires-Dist: pypinyin ==0.55.0
